firestarter_ui/__init__.py
firestarter_ui/__main__.py
firestarter_ui/firestarter_operations.py
firestarter_ui/main_app.py
firestarter_ui/operation_panels.py
firestarter_ui/ui_manager.py
firestarter_ui/icons/blank.png
firestarter_ui/icons/blank_check.png
firestarter_ui/icons/check_id.png
firestarter_ui/icons/erase.png
firestarter_ui/icons/logo_icon.png
firestarter_ui/icons/read.png
firestarter_ui/icons/verify.png
firestarter_ui/icons/write.png
firestarter_ui-0.1.17.dist-info/licenses/LICENSE
firestarter_ui-0.1.17.dist-info/METADATA
firestarter_ui-0.1.17.dist-info/WHEEL
firestarter_ui-0.1.17.dist-info/entry_points.txt
firestarter_ui-0.1.17.dist-info/top_level.txt
firestarter_ui-0.1.17.dist-info/RECORD
